i18n_updater_cn/__init__.py
i18n_updater_cn/config.py
i18n_updater_cn/main.py
i18n_updater_cn/resource_converter.py
i18n_updater_cn/resource_pack.py
i18n_updater_cn/utils.py
i18n_updater_cn/version.py
i18n_updater_cn-1.0.7.dist-info/licenses/LICENSE
i18n_updater_cn-1.0.7.dist-info/METADATA
i18n_updater_cn-1.0.7.dist-info/WHEEL
i18n_updater_cn-1.0.7.dist-info/entry_points.txt
i18n_updater_cn-1.0.7.dist-info/top_level.txt
i18n_updater_cn-1.0.7.dist-info/RECORD
