Metadata-Version: 2.4
Name: i18n-updater-cn
Version: 1.0.7
Summary: Minecraft模组汉化包更新器
Home-page: https://github.com/zack-zzq/I18nUpdatePython
Author: Zack Zhu
Author-email: kressety@163.com
Project-URL: Bug Tracker, https://github.com/zack-zzq/I18nUpdatePython/issues
Classifier: Programming Language :: Python :: 3
Classifier: Operating System :: OS Independent
Requires-Python: >=3.6
License-File: LICENSE
Requires-Dist: requests>=2.25.0
Dynamic: author
Dynamic: author-email
Dynamic: classifier
Dynamic: description
Dynamic: description-content-type
Dynamic: home-page
Dynamic: license-file
Dynamic: project-url
Dynamic: requires-dist
Dynamic: requires-python
Dynamic: summary
